xoflib-0.4.0.dist-info/METADATA
xoflib-0.4.0.dist-info/WHEEL
xoflib-0.4.0.dist-info/licenses/LICENSE
xoflib.libs/libgcc_s-5b5488a6.so.1
xoflib/__init__.py
xoflib/__init__.pyi
xoflib/py.typed
xoflib/xoflib.pypy39-pp73-arm-linux-gnu.so
xoflib-0.4.0.dist-info/RECORD
