Metadata-Version: 2.4
Name: xoflib
Version: 0.4.0
Classifier: Topic :: Security :: Cryptography
Classifier: Programming Language :: Rust
Classifier: Programming Language :: Python :: Implementation :: CPython
Classifier: Programming Language :: Python :: Implementation :: PyPy
Classifier: License :: OSI Approved :: MIT License
License-File: LICENSE
Summary: A package for the Shake and Ascon extendable-output functions (XOFs)
Requires-Python: >=3.9
Project-URL: Homepage, https://github.com/GiacomoPope/xoflib
Project-URL: Issues, https://github.com/GiacomoPope/xoflib/issues
